{
  "file_path": "C:\\Users\\DonBucknor_n0ufqwv\\GettingStarted\\ASEAGI\\PROJ344-Multi-dimensional-legal-document-scoring-system-s3.rtf",
  "file_name": "PROJ344-Multi-dimensional-legal-document-scoring-system-s3.rtf",
  "file_type": "rtf",
  "file_size": 59016,
  "file_hash": "497278ef13372747b82969288a5a5073",
  "extraction_date": "2025-11-06T09:18:56.437518",
  "extraction_method": "striprtf",
  "title": "FEDERAL LEGAL SCORING SYSTEMS + PRACTICAL RECOMMENDATIONS",
  "author": null,
  "created_date": "2025-11-05T11:53:59.544359",
  "modified_date": "2025-11-05T11:53:59.545359",
  "page_count": null,
  "word_count": 2719,
  "char_count": 24433
}